mqttbcp/__init__.py
mqttbcp/commands.py
mqttbcp/helper.py
mqttbcp-0.0.1.dist-info/LICENSE
mqttbcp-0.0.1.dist-info/METADATA
mqttbcp-0.0.1.dist-info/WHEEL
mqttbcp-0.0.1.dist-info/top_level.txt
mqttbcp-0.0.1.dist-info/RECORD
